r2g_gui/__init__.py
r2g_gui/main_window.py
r2g_gui/dialogs/__init__.py
r2g_gui/dialogs/ui_config.py
r2g_gui/fonts/Ubuntu.ttf
r2g_gui/fonts/UbuntuMono.ttf
r2g_gui/images/logo.icns
r2g_gui/images/logo.ico
r2g_gui/images/logo.png
r2g_gui/images/start.png
r2g_gui/images/stop.png
r2g_gui/main/__init__.py
r2g_gui/main/operations.py
r2g_gui/main/ui_main.py
r2g_gui/main/utils.py
r2g_gui-0.1.1.data/scripts/r2g.gui.py
r2g_gui-0.1.1.dist-info/LICENSE
r2g_gui-0.1.1.dist-info/METADATA
r2g_gui-0.1.1.dist-info/WHEEL
r2g_gui-0.1.1.dist-info/top_level.txt
r2g_gui-0.1.1.dist-info/RECORD
