Metadata-Version: 2.1
Name: r2g-gui
Version: 0.1.1
Summary: A GUI for r2g, which is a homology-based, computationally lightweight pipeline for discovering genes in the absence of an assembly
Home-page: https://github.com/yangwu91/r2g_gui.git
Author: Yang Wu
Author-email: wuyang@drwu.ga
Maintainer: Yang Wu
Maintainer-email: wuyang@drwu.ga
License: MIT
Platform: UNKNOWN
Classifier: Development Status :: 5 - Production/Stable
Classifier: Environment :: Console
Classifier: Intended Audience :: Science/Research
Classifier: License :: OSI Approved :: MIT License
Classifier: Natural Language :: English
Classifier: Operating System :: OS Independent
Classifier: Programming Language :: Python :: 3.6
Classifier: Programming Language :: Python :: 3.7
Classifier: Programming Language :: Python :: 3.8
Classifier: Programming Language :: Python :: 3.9
Classifier: Topic :: Scientific/Engineering :: Bio-Informatics
Requires-Python: >=3.6
Requires-Dist: PyQt5 (>=5.12)
Requires-Dist: docker[tls] (~=4.3.1)
Provides-Extra: cli
Requires-Dist: r2g (>=1.0.5) ; extra == 'cli'
Requires-Dist: requests (~=2.24.0) ; extra == 'cli'
Requires-Dist: selenium (~=3.141.0) ; extra == 'cli'
Provides-Extra: test
Requires-Dist: pytest ; extra == 'test'
Requires-Dist: pytest-cov ; extra == 'test'
Requires-Dist: codecov ; extra == 'test'
